stringliteral/__init__.py
stringliteral/stringliteral.py
stringliteral-0.0.1.dist-info/WHEEL
stringliteral-0.0.1.dist-info/METADATA
stringliteral-0.0.1.dist-info/RECORD
