Metadata-Version: 2.1
Name: stringliteral
Version: 0.0.1
Summary: stringliteral
Home-page: UNKNOWN
License: UNKNOWN
Author: Sander Teunissen
Requires-Python: >=3.7
Requires-Dist: pylint ; extra == "dev"
Requires-Dist: nox ; extra == "dev"
Requires-Dist: pytest-cov ; extra == "dev"
Requires-Dist: coverage[toml]>=5.0.3 ; extra == "dev"
Requires-Dist: pre-commit ; extra == "dev"
Requires-Dist: pytest ; extra == "test"
Requires-Dist: pytest-asyncio ; extra == "test"
Requires-Dist: pytest-mock ; extra == "test"
Provides-Extra: dev
Provides-Extra: test
